fast_ssg/__init__.py
fast_ssg/__main__.py
fast_ssg/text.py
fast_ssg/utils.py
fast_ssg-1.0.1.dist-info/LICENSE
fast_ssg-1.0.1.dist-info/METADATA
fast_ssg-1.0.1.dist-info/WHEEL
fast_ssg-1.0.1.dist-info/entry_points.txt
fast_ssg-1.0.1.dist-info/top_level.txt
fast_ssg-1.0.1.dist-info/RECORD
