Metadata-Version: 2.1
Name: fast-ssg
Version: 1.0.1
Summary: Fast Static Site Generator  - a tool for generating a complete HTML files from raw data like txt and markdown files.
Home-page: https://github.com/abatomunkuev/static_site_generator
Author: Andrei Batomunkuev
Author-email: andreibatomunkuev@gmail.com
License: UNKNOWN
Project-URL: Bug Tracker, https://github.com/abatomunkuev/static_site_generator/issues
Platform: UNKNOWN
Classifier: Programming Language :: Python :: 3
Classifier: License :: OSI Approved :: MIT License
Classifier: Operating System :: OS Independent
Requires-Python: >=3.6
License-File: LICENSE
Requires-Dist: beautifulsoup4 (==4.10.0)
